LICENSE
README.md
pyproject.toml
setup.py
cold_war_zombies.egg-info/PKG-INFO
cold_war_zombies.egg-info/SOURCES.txt
cold_war_zombies.egg-info/dependency_links.txt
cold_war_zombies.egg-info/top_level.txt
zombie/analysis.py
zombie/base.py
zombie/health_armour.py
zombie/modified_weapon.py
zombie/processor.py
zombie/weapon_stats.py