Metadata-Version: 2.1
Name: cold-war-zombies
Version: 1.0.1
Summary: A package for comparing weapons in Call of Duty Cold War Zombies
Home-page: https://medium.com/@peterjrigali/best-weapon-in-zombies-9fddd33735c5
Author: Peter Rigali
Author-email: peterjrigali@gmail.com
License: MIT
Platform: UNKNOWN
License-File: LICENSE
